ShejiaoRuanjianBameiGonglue/README.md
ShejiaoRuanjianBameiGonglue/__init__.py
ShejiaoRuanjianBameiGonglue/__main__.py
ShejiaoRuanjianBameiGonglue/file.epub
ShejiaoRuanjianBameiGonglue/index.html
ShejiaoRuanjianBameiGonglue/css/__init__.py
ShejiaoRuanjianBameiGonglue/css/annotations.css
ShejiaoRuanjianBameiGonglue/css/main.css
ShejiaoRuanjianBameiGonglue/css/normalize.css
ShejiaoRuanjianBameiGonglue/css/popup.css
ShejiaoRuanjianBameiGonglue/font/__init__.py
ShejiaoRuanjianBameiGonglue/font/fontello.eot
ShejiaoRuanjianBameiGonglue/font/fontello.svg
ShejiaoRuanjianBameiGonglue/font/fontello.ttf
ShejiaoRuanjianBameiGonglue/font/fontello.woff
ShejiaoRuanjianBameiGonglue/img/__init__.py
ShejiaoRuanjianBameiGonglue/img/annotator-glyph-sprite.png
ShejiaoRuanjianBameiGonglue/img/annotator-icon-sprite.png
ShejiaoRuanjianBameiGonglue/img/apple-touch-icon.png
ShejiaoRuanjianBameiGonglue/img/cancelfullscreen.png
ShejiaoRuanjianBameiGonglue/img/close.png
ShejiaoRuanjianBameiGonglue/img/fullscreen.png
ShejiaoRuanjianBameiGonglue/img/loader.gif
ShejiaoRuanjianBameiGonglue/img/menu-icon.png
ShejiaoRuanjianBameiGonglue/img/save.png
ShejiaoRuanjianBameiGonglue/img/saved.png
ShejiaoRuanjianBameiGonglue/img/settings-s.png
ShejiaoRuanjianBameiGonglue/img/settings.png
ShejiaoRuanjianBameiGonglue/img/star.png
ShejiaoRuanjianBameiGonglue/js/__init__.py
ShejiaoRuanjianBameiGonglue/js/epub.js
ShejiaoRuanjianBameiGonglue/js/epub.min.js
ShejiaoRuanjianBameiGonglue/js/epub.min.map
ShejiaoRuanjianBameiGonglue/js/hooks.min.js
ShejiaoRuanjianBameiGonglue/js/hooks.min.map
ShejiaoRuanjianBameiGonglue/js/reader.js
ShejiaoRuanjianBameiGonglue/js/reader.js.map
ShejiaoRuanjianBameiGonglue/js/reader.min.js
ShejiaoRuanjianBameiGonglue/js/reader.min.map
ShejiaoRuanjianBameiGonglue/js/hooks/__init__.py
ShejiaoRuanjianBameiGonglue/js/hooks/extensions/__init__.py
ShejiaoRuanjianBameiGonglue/js/hooks/extensions/highlight.js
ShejiaoRuanjianBameiGonglue/js/libs/__init__.py
shejiao_ruanjian_bamei_gonglue-2022.10.11.0.dist-info/METADATA
shejiao_ruanjian_bamei_gonglue-2022.10.11.0.dist-info/WHEEL
shejiao_ruanjian_bamei_gonglue-2022.10.11.0.dist-info/entry_points.txt
shejiao_ruanjian_bamei_gonglue-2022.10.11.0.dist-info/top_level.txt
shejiao_ruanjian_bamei_gonglue-2022.10.11.0.dist-info/RECORD
